{
  "id": "36d3-36bc-68dd-40ac",
  "name": "Adeptus Astartes - Black Templars",
  "catalogueName": "Imperium - Adeptus Astartes - Black Templars",
  "units": [
    {
      "id": "8165-e372-4fd6-3274",
      "name": "Chaplain Grimaldus",
      "points": 110,
      "keywords": [
        "Infantry",
        "Imperium",
        "Tacticus"
      ],
      "factionKeywords": [
        "Adeptus Astartes",
        "Black Templars"
      ],
      "stats": {
        "M": "6\"",
        "T": "4",
        "SV": "3+",
        "W": "4",
        "LD": "5+",
        "OC": "1"
      },
      "rangedWeapons": [
        {
          "name": "Plasma Pistol - Supercharge",
          "range": "12\"",
          "A": "1",
          "BS": "2+",
          "S": "8",
          "AP": "-3",
          "D": "2",
          "keywords": [
            "Hazardous",
            "Pistol"
          ]
        },
        {
          "name": "Plasma Pistol - Standard",
          "range": "12\"",
          "A": "1",
          "BS": "2+",
          "S": "7",
          "AP": "-2",
          "D": "1",
          "keywords": [
            "Pistol"
          ]
        }
      ],
      "meleeWeapons": [
        {
          "name": "Artificer Crozius",
          "range": "Melee",
          "A": "6",
          "WS": "2+",
          "S": "6",
          "AP": "-2",
          "D": "2",
          "keywords": []
        },
        {
          "name": "Close Combat Weapon",
          "range": "Melee",
          "A": "1",
          "WS": "4+",
          "S": "3",
          "AP": "0",
          "D": "1",
          "keywords": []
        }
      ],
      "abilities": [
        {
          "name": "Litanies of the Devout",
          "description": "While this unit is leading a unit and contains a Chaplain Grimaldus model, each time a model in that unit makes a melee attack, you can re-roll the Hit roll."
        },
        {
          "name": "Temple Relics",
          "description": "In your Command phase, if this unit contains one or more Cenobyte Servitor models, select one Temple Relics ability (see left). Until the start of your next Command phase, this unit’s Chaplain Grimaldus model has that ability.\n\n\nBanner of the Emperor Victorious: Add 1 to Advance and Charge rolls for this unit\n\n\nColumn of the Major Alter: Add 1 to the Toughness characteristic of models in this unit\n\n\nWater from the Stoup of Elucidation: Improve the Armour Penetration characteristic of melee weapons equipped by models in this unit by 1."
        },
        {
          "name": "Leader",
          "description": "This unit can be attached to the following units:\n\n■ Assault Intercessor Squad\n■ Infernus Squad\n■ Intercessor Squad\n■ Crusader Squad\n■ Sword Brethren"
        }
      ],
      "pricing": [
        {
          "range": "[1,)",
          "label": "Your Unit Costs",
          "costs": [
            {
              "models": 4,
              "points": 110
            }
          ]
        }
      ],
      "pointsLabel": "110",
      "mfmRole": "leader",
      "attachTo": [
        "Assault Intercessor Squad",
        "Crusader Squad",
        "Infernus Squad",
        "Intercessor Squad",
        "Sword Brethren Squad"
      ]
    },
    {
      "id": "da8a-de9f-1fe7-2513",
      "name": "High Marshal Helbrecht",
      "points": 120,
      "keywords": [
        "Epic Hero",
        "Character",
        "Grenades",
        "Imperium",
        "Tacticus",
        "Infantry",
        "Chapter Master"
      ],
      "factionKeywords": [
        "Adeptus Astartes",
        "Black Templars"
      ],
      "stats": {
        "M": "6\"",
        "T": "4",
        "SV": "2+",
        "W": "6",
        "LD": "6+",
        "OC": "3"
      },
      "rangedWeapons": [
        {
          "name": "Ferocity",
          "range": "24\"",
          "A": "2",
          "BS": "2+",
          "S": "5",
          "AP": "-1",
          "D": "2",
          "keywords": [
            "Anti-infantry 4+",
            "Devastating Wounds"
          ]
        }
      ],
      "meleeWeapons": [
        {
          "name": "Sword of the High Marshals - Sweep",
          "range": "Melee",
          "A": "12",
          "WS": "2+",
          "S": "6",
          "AP": "-3",
          "D": "1",
          "keywords": []
        },
        {
          "name": "Sword of the High Marshals - Strike",
          "range": "Melee",
          "A": "6",
          "WS": "2+",
          "S": "8",
          "AP": "-3",
          "D": "3",
          "keywords": []
        }
      ],
      "abilities": [
        {
          "name": "Crusade of Wrath",
          "description": "While this model is leading a unit, add 1 to the Attacks and Strength characteristic of melee weapons equipped by models in that unit."
        },
        {
          "name": "High Marshal",
          "description": "At the start of the Fight phase, select one enemy unit within Engagement Range of this model’s unit and roll one D6, adding 1 to the result for every five models in this model's unit: on a 2-3, that enemy unit suffers D3 mortal wounds; on a 4-5, that enemy unit suffers 3 mortal wounds; on a 6, that enemy unit suffers D3+3 mortal wounds."
        },
        {
          "name": "Leader",
          "description": "This model can be attached to the following units:\n\n■ Assault Intercessor Squad\n■ Intercessor Squad\n■ Crusader Squad\n■ Sword Brethren"
        }
      ],
      "pricing": [
        {
          "range": "[1,)",
          "label": "Your Unit Costs",
          "costs": [
            {
              "models": 1,
              "points": 120
            }
          ]
        }
      ],
      "pointsLabel": "120",
      "mfmRole": "leader",
      "attachTo": [
        "Assault Intercessor Squad",
        "Crusader Squad",
        "Intercessor Squad",
        "Sword Brethren Squad"
      ]
    },
    {
      "id": "8bbe-e7fc-44b7-ed94",
      "name": "Crusader Squad",
      "points": 150,
      "keywords": [
        "Infantry",
        "Battleline",
        "Grenades",
        "Imperium",
        "Tacticus"
      ],
      "factionKeywords": [
        "Adeptus Astartes",
        "Black Templars"
      ],
      "stats": {
        "M": "6\"",
        "T": "4",
        "SV": "3+",
        "W": "2",
        "LD": "6+",
        "OC": "2"
      },
      "rangedWeapons": [
        {
          "name": "Pyre Pistol",
          "range": "12\"",
          "A": "D6",
          "BS": "N/A",
          "S": "4",
          "AP": "0",
          "D": "1",
          "keywords": [
            "Ignores Cover",
            "Pistol",
            "Torrent"
          ]
        }
      ],
      "meleeWeapons": [
        {
          "name": "Master-crafted Power Weapon",
          "range": "Melee",
          "A": "3",
          "WS": "2+",
          "S": "5",
          "AP": "-2",
          "D": "2",
          "keywords": [
            "Lethal Hits"
          ]
        }
      ],
      "abilities": [
        {
          "name": "Righteous Zeal",
          "description": "In your opponent's Shooting phase, each time an enemy unit has shot, if any models from this unit were destroyed as a result of those attacks, this unit can make a Righteous Zeal move. To do so, roll one D6 and add 2 to the result: models in this unit move a number of inches up to this result, but this unit must end that move as close as possible to the closest enemy unit (excluding ^^**Aircraft^^**). When doing so, those models can be moved within Engagement Range of that enemy unit. This unit cannot make a Righteous Zeal move while it is Battle-shocked or within Engagement Range of one or more enemy units, and can only make one Righteous Zeal move per phase."
        }
      ],
      "pricing": [
        {
          "range": "[1,)",
          "label": "Your Unit Costs",
          "costs": [
            {
              "models": 10,
              "points": 150,
              "desc": "1 Sword Brother, 4 Neophytes, 5 Initiates"
            },
            {
              "models": 20,
              "points": 290,
              "desc": "1 Sword Brother, 8 Neophytes, 11 Initiates"
            }
          ]
        }
      ],
      "pointsLabel": "150/290"
    },
    {
      "id": "206c-6b4d-4aaa-7e79",
      "name": "Sword Brethren Squad",
      "points": 105,
      "keywords": [
        "Infantry",
        "Grenades",
        "Imperium",
        "Tacticus",
        "Primaris Sword Brethren"
      ],
      "factionKeywords": [
        "Adeptus Astartes",
        "Black Templars"
      ],
      "stats": {
        "M": "6\"",
        "T": "4",
        "SV": "3+",
        "W": "3",
        "LD": "6+",
        "OC": "1"
      },
      "rangedWeapons": [
        {
          "name": "Pyre Pistol",
          "range": "12\"",
          "A": "D6",
          "BS": "N/A",
          "S": "4",
          "AP": "0",
          "D": "1",
          "keywords": [
            "Ignores Cover",
            "Pistol",
            "Torrent"
          ]
        }
      ],
      "meleeWeapons": [
        {
          "name": "Thunder Hammer",
          "range": "Melee",
          "A": "3",
          "WS": "3+",
          "S": "8",
          "AP": "-2",
          "D": "2",
          "keywords": [
            "Devastating Wounds"
          ]
        },
        {
          "name": "Master-crafted Power Weapon",
          "range": "Melee",
          "A": "3",
          "WS": "2+",
          "S": "5",
          "AP": "-2",
          "D": "2",
          "keywords": [
            "Lethal Hits"
          ]
        },
        {
          "name": "Astartes Chainsword",
          "range": "Melee",
          "A": "6",
          "WS": "2+",
          "S": "4",
          "AP": "-1",
          "D": "1",
          "keywords": [
            "Sustained Hits 1"
          ]
        },
        {
          "name": "Twin Lightning Claws",
          "range": "Melee",
          "A": "5",
          "WS": "2+",
          "S": "5",
          "AP": "-2",
          "D": "1",
          "keywords": [
            "Twin-linked"
          ]
        }
      ],
      "abilities": [
        {
          "name": "Exploit Their Cowardice",
          "description": "Each time an enemy unit within Engagement Range of this unit is selected to Fall Back, after it ends that Fall Back move, if this unit is not within Engagement Range of one or more enemy units, this unit can make a Normal move."
        }
      ],
      "pricing": [
        {
          "range": "[1,2]",
          "label": "Your 1st To 2nd Units Cost",
          "costs": [
            {
              "models": 4,
              "points": 105
            },
            {
              "models": 5,
              "points": 130
            },
            {
              "models": 9,
              "points": 235
            },
            {
              "models": 10,
              "points": 260
            }
          ]
        },
        {
          "range": "[3,)",
          "label": "Your 3rd + Unit Costs",
          "costs": [
            {
              "models": 4,
              "points": 120
            },
            {
              "models": 5,
              "points": 145
            },
            {
              "models": 9,
              "points": 250
            },
            {
              "models": 10,
              "points": 275
            }
          ]
        }
      ],
      "pointsLabel": "105/130/235/260"
    },
    {
      "id": "ca2f-f408-c1bd-b87f",
      "name": "Emperor's Champion",
      "points": 100,
      "keywords": [
        "Character",
        "Infantry",
        "Grenades",
        "Imperium",
        "Tacticus"
      ],
      "factionKeywords": [
        "Adeptus Astartes",
        "Black Templars"
      ],
      "stats": {
        "M": "8\"",
        "T": "4",
        "SV": "2+",
        "W": "5",
        "LD": "6+",
        "OC": "1"
      },
      "rangedWeapons": [],
      "meleeWeapons": [
        {
          "name": "Black Sword - Strike",
          "range": "Melee",
          "A": "6",
          "WS": "2+",
          "S": "8",
          "AP": "-3",
          "D": "3",
          "keywords": [
            "Anti-Character 5+",
            "Precision"
          ]
        },
        {
          "name": "Black Sword - Sweep",
          "range": "Melee",
          "A": "10",
          "WS": "2+",
          "S": "6",
          "AP": "-2",
          "D": "1",
          "keywords": []
        }
      ],
      "abilities": [
        {
          "name": "Armour of Faith",
          "description": "Once per phase, when an attack is allocated to this model and the saving throw is failed, you can change the Damage characteristic of that attack to 0."
        },
        {
          "name": "Sigismund's Heir",
          "description": "Each time this model's unit declares a charge, if one or more targets of that charge have the CHARACTER keyword, add 2 to the Charge roll. Once per battle, when this model's unit is selected to fight, if that unit is within Engagement Range of one or more enemy CHARACTER units, this model can use this ability. If it does, until the end of the phase, melee weapons equipped by this model have the [DEVASTATING WOUNDS] ability."
        },
        {
          "name": "Leader",
          "description": "This model can be attached to the following units:\n\n■ Assault Intercessor Squad\n■ Intercessor Squad\n■ Crusader Squad\n■ Sword Brethren\n■ Sternguard Veteran Squad"
        },
        {
          "name": "Chosen of the Emperor",
          "description": "You cannot include more than one **^^Emperor's Champion^^** model in your army."
        }
      ],
      "pricing": [
        {
          "range": "[1,)",
          "label": "Your Unit Costs",
          "costs": [
            {
              "models": 1,
              "points": 100
            }
          ]
        }
      ],
      "pointsLabel": "100",
      "mfmRole": "leader",
      "attachTo": [
        "Assault Intercessor Squad",
        "Crusader Squad",
        "Intercessor Squad",
        "Sternguard Veteran Squad",
        "Sword Brethren Squad"
      ]
    },
    {
      "id": "2da2-ad08-6057-5a1c",
      "name": "Crusader Squad [Legends]",
      "points": 85,
      "keywords": [
        "Infantry",
        "Battleline",
        "Grenades",
        "Imperium",
        "Crusader Squad"
      ],
      "factionKeywords": [
        "Adeptus Astartes",
        "Black Templars"
      ],
      "stats": {
        "M": "6\"",
        "T": "4",
        "SV": "4+",
        "W": "2",
        "LD": "6+",
        "OC": "2"
      },
      "rangedWeapons": [
        {
          "name": "Astartes Shotgun",
          "range": "18",
          "A": "2",
          "BS": "3+",
          "S": "4",
          "AP": "0",
          "D": "1",
          "keywords": [
            "Assault"
          ]
        }
      ],
      "meleeWeapons": [
        {
          "name": "Combat Knife",
          "range": "Melee",
          "A": "3",
          "WS": "3+",
          "S": "4",
          "AP": "-1",
          "D": "1",
          "keywords": []
        },
        {
          "name": "Twin Lightning Claws",
          "range": "Melee",
          "A": "3",
          "WS": "3+",
          "S": "4",
          "AP": "-2",
          "D": "1",
          "keywords": [
            "Twin-linked"
          ]
        }
      ],
      "abilities": [
        {
          "name": "Righteous Zeal",
          "description": "You can re-roll Advance and Charge rolls made for this unit."
        }
      ]
    },
    {
      "id": "7dec-dc3d-c40a-8ce",
      "name": "Gladiator Lancer",
      "points": 160,
      "keywords": [
        "Vehicle",
        "Imperium",
        "Smoke"
      ],
      "factionKeywords": [
        "Adeptus Astartes",
        "Black Templars"
      ],
      "stats": {
        "M": "10\"",
        "T": "10",
        "SV": "3+",
        "W": "12",
        "LD": "6+",
        "OC": "3"
      },
      "rangedWeapons": [
        {
          "name": "Lancer Laser Destroyer",
          "range": "72\"",
          "A": "2",
          "BS": "3+",
          "S": "14",
          "AP": "-4",
          "D": "D6+3",
          "keywords": [
            "Heavy"
          ]
        }
      ],
      "meleeWeapons": [],
      "abilities": [
        {
          "name": "Aquilon Optics",
          "description": "Each time this model is selected to shoot, you can re-roll one Hit roll, you can re-roll one Wound roll and you can re-roll one Damage roll when resolving its attacks"
        }
      ],
      "pricing": [
        {
          "range": "[1,2]",
          "label": "Your 1st To 2nd Units Cost",
          "costs": [
            {
              "models": 1,
              "points": 160
            }
          ]
        },
        {
          "range": "[3,)",
          "label": "Your 3rd + Unit Costs",
          "costs": [
            {
              "models": 1,
              "points": 170
            }
          ]
        }
      ],
      "pointsLabel": "160"
    },
    {
      "id": "bfb6-4320-74cf-bbda",
      "name": "Gladiator Reaper",
      "points": 160,
      "keywords": [
        "Smoke",
        "Imperium",
        "Vehicle"
      ],
      "factionKeywords": [
        "Adeptus Astartes",
        "Black Templars"
      ],
      "stats": {
        "M": "10\"",
        "T": "10",
        "SV": "3+",
        "W": "12",
        "LD": "6+",
        "OC": "3"
      },
      "rangedWeapons": [
        {
          "name": "Tempest Bolter",
          "range": "24\"",
          "A": "4",
          "BS": "3+",
          "S": "4",
          "AP": "-1",
          "D": "1",
          "keywords": [
            "Rapid Fire 4"
          ]
        },
        {
          "name": "Twin Heavy Onslaught Gatling Cannon",
          "range": "24\"",
          "A": "12",
          "BS": "3+",
          "S": "6",
          "AP": "0",
          "D": "1",
          "keywords": [
            "Devastating Wounds",
            "Twin-linked"
          ]
        }
      ],
      "meleeWeapons": [],
      "abilities": [
        {
          "name": "Rotating Death",
          "description": "This model’s twin heavy onslaught gatling cannon has the [SUSTAINED HITS 2] ability when targeting Infantry units."
        }
      ],
      "pricing": [
        {
          "range": "[1,2]",
          "label": "Your 1st To 2nd Units Cost",
          "costs": [
            {
              "models": 1,
              "points": 160
            }
          ]
        },
        {
          "range": "[3,)",
          "label": "Your 3rd + Unit Costs",
          "costs": [
            {
              "models": 1,
              "points": 170
            }
          ]
        }
      ],
      "pointsLabel": "160"
    },
    {
      "id": "5704-ffe4-4a53-8789",
      "name": "Gladiator Valiant",
      "points": 150,
      "keywords": [
        "Vehicle",
        "Smoke",
        "Imperium"
      ],
      "factionKeywords": [
        "Adeptus Astartes",
        "Black Templars"
      ],
      "stats": {
        "M": "10\"",
        "T": "10",
        "SV": "3+",
        "W": "12",
        "LD": "6+",
        "OC": "3"
      },
      "rangedWeapons": [
        {
          "name": "Twin Las-talon",
          "range": "36\"",
          "A": "2",
          "BS": "3+",
          "S": "10",
          "AP": "-3",
          "D": "D6+1",
          "keywords": [
            "Twin-linked"
          ]
        }
      ],
      "meleeWeapons": [],
      "abilities": [
        {
          "name": "Ferocious Assault",
          "description": "Each time this model makes an attack with its twin las-talon that targets the closest eligible Monster or Vehicle unit, add 1 to the Hit roll"
        }
      ],
      "pricing": [
        {
          "range": "[1,2]",
          "label": "Your 1st To 2nd Units Cost",
          "costs": [
            {
              "models": 1,
              "points": 150
            }
          ]
        },
        {
          "range": "[3,)",
          "label": "Your 3rd + Unit Costs",
          "costs": [
            {
              "models": 1,
              "points": 160
            }
          ]
        }
      ],
      "pointsLabel": "150"
    },
    {
      "id": "fa27-4bc1-72c9-894f",
      "name": "Impulsor",
      "points": 80,
      "keywords": [
        "Vehicle",
        "Transport",
        "Dedicated Transport",
        "Imperium"
      ],
      "factionKeywords": [
        "Adeptus Astartes",
        "Black Templars"
      ],
      "stats": {
        "M": "12\"",
        "T": "9",
        "SV": "3+",
        "W": "11",
        "LD": "6+",
        "OC": "2"
      },
      "rangedWeapons": [],
      "meleeWeapons": [],
      "abilities": [
        {
          "name": "Transport",
          "description": "This model has a transport capacity of 7 TACTICUS or PHOBOS INFANTRY models. It cannot transport JUMP PACK models."
        },
        {
          "name": "Assault Vehicle",
          "description": "Units can disembark from this Transport after it has Advanced. Units that do so count as having made a Normal move, and cannot declare a charge that turn."
        }
      ],
      "pricing": [
        {
          "range": "[1,)",
          "label": "Your Unit Costs",
          "costs": [
            {
              "models": 1,
              "points": 80
            }
          ]
        }
      ],
      "pointsLabel": "80"
    },
    {
      "id": "c3e8-3cde-8b39-4b19",
      "name": "Repulsor",
      "points": 170,
      "keywords": [
        "Vehicle",
        "Imperium",
        "Smoke",
        "Transport"
      ],
      "factionKeywords": [
        "Adeptus Astartes",
        "Black Templars"
      ],
      "stats": {
        "M": "10\"",
        "T": "12",
        "SV": "3+",
        "W": "16",
        "LD": "6+",
        "OC": "5"
      },
      "rangedWeapons": [
        {
          "name": "Twin Las-talon",
          "range": "36\"",
          "A": "2",
          "BS": "3+",
          "S": "10",
          "AP": "-3",
          "D": "D6+1",
          "keywords": [
            "Twin-linked"
          ]
        }
      ],
      "meleeWeapons": [],
      "abilities": [
        {
          "name": "Transport",
          "description": "This model has a transport capacity of 14 ADEPTUS ASTARTES INFANTRY models. Each JUMP PACK, GRAVIS or TERMINATOR model takes up the space of 2 models and each CENTURION model takes up the space of 3 models."
        },
        {
          "name": "Stabilised Disembarkation",
          "description": "In your opponent's Shooting phase, each time and enemy unit is selected to shoot, after that unit has shot, if any of those attacks targeted this TRANSPORT, it can use this ability. If it does, any units embarked within it can disembark. When doing so, models in those units can be set up wholly within 6\" of this TRANSPORT and not within Engagement Range of one or more enemy units."
        }
      ],
      "pricing": [
        {
          "range": "[1,2]",
          "label": "Your 1st To 2nd Units Cost",
          "costs": [
            {
              "models": 1,
              "points": 170
            }
          ]
        },
        {
          "range": "[3,)",
          "label": "Your 3rd + Unit Costs",
          "costs": [
            {
              "models": 1,
              "points": 190
            }
          ]
        }
      ],
      "pointsLabel": "170"
    },
    {
      "id": "a344-192f-aae2-16e5",
      "name": "Repulsor Executioner",
      "points": 240,
      "keywords": [
        "Vehicle",
        "Smoke",
        "Imperium",
        "Transport"
      ],
      "factionKeywords": [
        "Adeptus Astartes",
        "Black Templars"
      ],
      "stats": {
        "M": "10\"",
        "T": "12",
        "SV": "3+",
        "W": "16",
        "LD": "6+",
        "OC": "5"
      },
      "rangedWeapons": [
        {
          "name": "Repulsor Executioner Defensive Array",
          "range": "24\"",
          "A": "10",
          "BS": "3+",
          "S": "4",
          "AP": "0",
          "D": "1",
          "keywords": []
        }
      ],
      "meleeWeapons": [],
      "abilities": [
        {
          "name": "Transport",
          "description": "This model has a transport capacity of 7 Adeptus Astartes Infantry models. Each Jump Pack, Wulfen, Gravis or Terminator model takes up the space of 2 models and each Centurion model takes up the space of 3 models."
        },
        {
          "name": "Interception Strike",
          "description": "Each time this model makes a ranged attack that targets a unit that is within 12\" of one or more ADEPTUS ASTARTES units from your army, you can re-roll the Hit roll."
        }
      ],
      "pricing": [
        {
          "range": "[1,2]",
          "label": "Your 1st To 2nd Units Cost",
          "costs": [
            {
              "models": 1,
              "points": 240
            }
          ]
        },
        {
          "range": "[3,)",
          "label": "Your 3rd + Unit Costs",
          "costs": [
            {
              "models": 1,
              "points": 260
            }
          ]
        }
      ],
      "pointsLabel": "240"
    },
    {
      "id": "f151-e676-d3b8-200c",
      "name": "Castellan",
      "points": 70,
      "keywords": [
        "Character",
        "Infantry",
        "Grenades",
        "Imperium",
        "Tacticus",
        "Lieutenant"
      ],
      "factionKeywords": [
        "Adeptus Astartes",
        "Black Templars"
      ],
      "stats": {
        "M": "6\"",
        "T": "4",
        "SV": "3+",
        "W": "4",
        "LD": "6+",
        "OC": "1"
      },
      "rangedWeapons": [],
      "meleeWeapons": [
        {
          "name": "Master-crafted Power Weapon",
          "range": "Melee",
          "A": "3",
          "WS": "2+",
          "S": "5",
          "AP": "-2",
          "D": "2",
          "keywords": [
            "Lethal Hits"
          ]
        }
      ],
      "abilities": [
        {
          "name": "Leader",
          "description": "This model can be attached to the following units:\n\n■ Assault Intercessor Squad\n■ Infernus Squad\n■ Intercessor Squad\n■ Crusader Squad\n■ Sword Brethren\n■ Sternguard Veteran Squad\n\nYou can attach this model to one of the above units even if one Captain or Chapter Master model has already been attached to it. If you do, and that Bodyguard unit is destroyed, the Leader units attached to it become separate units, with their original Starting Strengths."
        },
        {
          "name": "Vehement Aggression",
          "description": "While this model is leading a unit, each time that unit is selected to fight, take a Leadership test for that unit: if passed, until the end of the phase, each time a model in that unit makes an attack, you can re-roll the Hit roll; if failed, until the end of the phase, each time a model in that unit makes an attack, re-roll a Hit roll of 1"
        },
        {
          "name": "Prioritised Eradication",
          "description": "Each time a model in this model's unit makes a melee attack that destroys one or more enemy units, roll one D6: on a 4+, you gain 1 CP"
        }
      ],
      "pricing": [
        {
          "range": "[1,)",
          "label": "Your Unit Costs",
          "costs": [
            {
              "models": 1,
              "points": 70
            }
          ]
        }
      ],
      "pointsLabel": "70",
      "mfmRole": "support",
      "attachTo": [
        "Assault Intercessor Squad",
        "Crusader Squad",
        "Infernus Squad",
        "Intercessor Squad",
        "Sternguard Veteran Squad",
        "Sword Brethren Squad"
      ]
    },
    {
      "id": "68dd-5f49-4f17-cd84",
      "name": "Marshal",
      "points": 80,
      "keywords": [
        "Character",
        "Infantry",
        "Grenades",
        "Imperium",
        "Tacticus",
        "Captain"
      ],
      "factionKeywords": [
        "Adeptus Astartes",
        "Black Templars"
      ],
      "stats": {
        "M": "6\"",
        "T": "4",
        "SV": "3+",
        "W": "5",
        "LD": "6+",
        "OC": "1"
      },
      "rangedWeapons": [],
      "meleeWeapons": [
        {
          "name": "Master-crafted Power Weapon",
          "range": "Melee",
          "A": "7",
          "WS": "2+",
          "S": "5",
          "AP": "-2",
          "D": "2",
          "keywords": [
            "Lethal Hits"
          ]
        }
      ],
      "abilities": [
        {
          "name": "Leader",
          "description": "This model can be attached to the following units:\n\n■ Assault Intercessor Squad\n■ Infernus Squad\n■ Intercessor Squad\n■ Crusader Squad\n■ Sword Brethren\n■ Sternguard Veteran Squad"
        },
        {
          "name": "Inspirational Exemplar",
          "description": "While this model is leading a unit, each time a model in that unit makes a melee attack, an unmodified Hit roll of 5+ scores a Critical Hit."
        },
        {
          "name": "Pious Fervour",
          "description": "Each time this model's unit is selected to fight, until the end of the phase, add 1 to the Attacks characteristic of this model's Master-Crafted Power Weapon for each enemy unit within 6\" of this model (to a maximum of +3)"
        }
      ],
      "pricing": [
        {
          "range": "[1,1]",
          "label": "Your 1st Unit Costs",
          "costs": [
            {
              "models": 1,
              "points": 80
            }
          ]
        },
        {
          "range": "[2,)",
          "label": "Your 2nd + Unit Costs",
          "costs": [
            {
              "models": 1,
              "points": 90
            }
          ]
        }
      ],
      "pointsLabel": "80",
      "mfmRole": "leader",
      "attachTo": [
        "Assault Intercessor Squad",
        "Crusader Squad",
        "Infernus Squad",
        "Intercessor Squad",
        "Sternguard Veteran Squad",
        "Sword Brethren Squad"
      ]
    },
    {
      "id": "ea3d-f2b8-cce7-0762",
      "name": "Execrator",
      "points": 60,
      "keywords": [
        "Infantry",
        "Character",
        "Chaplain",
        "Grenades",
        "Imperium",
        "Tacticus"
      ],
      "factionKeywords": [
        "Adeptus Astartes",
        "Black Templars"
      ],
      "stats": {
        "M": "6\"",
        "T": "4",
        "SV": "3+",
        "W": "4",
        "LD": "5+",
        "OC": "1"
      },
      "rangedWeapons": [],
      "meleeWeapons": [
        {
          "name": "Master-crafted Power Weapon",
          "range": "Melee",
          "A": "3",
          "WS": "2+",
          "S": "5",
          "AP": "-2",
          "D": "2",
          "keywords": [
            "Extra Attacks",
            "Lethal Hits"
          ]
        }
      ],
      "abilities": [
        {
          "name": "Leader",
          "description": "This model can be attached to the following units:\n\n■ Crusader Squad\n■ Sword Brethren"
        },
        {
          "name": "Remorseless Persecution",
          "description": "While this model is leading a unit, that unit is eligible to declare a charge in a turn in which it Advanced"
        },
        {
          "name": "Condemnatory Annihilation",
          "description": "Each time this model's unit has fought, if one or more enemy units were destroyed as a result of those attacks, each enemy unit within 6\" of this model must take a Battle-shock test"
        }
      ],
      "pricing": [
        {
          "range": "[1,)",
          "label": "Your Unit Costs",
          "costs": [
            {
              "models": 1,
              "points": 60
            }
          ]
        }
      ],
      "pointsLabel": "60",
      "mfmRole": "leader",
      "attachTo": [
        "Crusader Squad",
        "Sword Brethren Squad"
      ]
    },
    {
      "id": "dca2-b12f-d1a9-5822",
      "name": "Crusade Ancient",
      "points": 45,
      "keywords": [
        "Character",
        "Infantry",
        "Grenades",
        "Ancient",
        "Tacticus",
        "Imperium"
      ],
      "factionKeywords": [
        "Adeptus Astartes",
        "Black Templars"
      ],
      "stats": {
        "M": "6\"",
        "T": "4",
        "SV": "3+",
        "W": "4",
        "LD": "6+",
        "OC": "1"
      },
      "rangedWeapons": [],
      "meleeWeapons": [
        {
          "name": "Master-crafted Power Weapon",
          "range": "Melee",
          "A": "5",
          "WS": "2+",
          "S": "5",
          "AP": "-2",
          "D": "2",
          "keywords": [
            "Lethal Hits"
          ]
        }
      ],
      "abilities": [
        {
          "name": "Vengeful Exhortation",
          "description": "While this model is leading a unit, each time a model in that unit is destroyed by a melee attack, if it has not fought this phase, roll one D6: on a 4+, do not remove it from play, the destroyed model can fight after the attacking unit has finished making its attacks, and is then removed from play."
        },
        {
          "name": "Martial Honour",
          "description": "The first time a model in this model's unit makes a melee attack that destroys one or more enemy units, until the end of the battle, while this model's unit is not Battle-shocked, add 5 to this model's Objective Control characteristic."
        },
        {
          "name": "Leader",
          "description": "This model can be attached to the following units:\n\n\n■ Crusader Squad\n■ Sword Brethren Squad\n\n\nYou can attach this model to one of the above units even if one Captain, Chapter Master, Execrator or Lieutenant model has already been attached to it. If you do, and that Bodyguard unit is destroyed, the Leader units attached to it become separate units, with their original Starting Strengths."
        }
      ],
      "pricing": [
        {
          "range": "[1,)",
          "label": "Your Unit Costs",
          "costs": [
            {
              "models": 1,
              "points": 45
            }
          ]
        }
      ],
      "pointsLabel": "45",
      "mfmRole": "support",
      "attachTo": [
        "Crusader Squad",
        "Sword Brethren Squad"
      ]
    },
    {
      "id": "8525-2de1-14fd-c1f5",
      "name": "Land Raider Crusader",
      "points": 220,
      "keywords": [
        "Vehicle",
        "Smoke",
        "Imperium",
        "Transport",
        "Grenades",
        "Land Raider"
      ],
      "factionKeywords": [
        "Adeptus Astartes",
        "Black Templars"
      ],
      "stats": {
        "M": "12\"",
        "T": "12",
        "SV": "2+",
        "W": "16",
        "LD": "6+",
        "OC": "5"
      },
      "rangedWeapons": [],
      "meleeWeapons": [],
      "abilities": [
        {
          "name": "Transport",
          "description": "This model has a transport capacity of 16 Adeptus Astartes Infantry models. Each Jump Pack, Wulfen, Gravis or Terminator model takes up the space of 2 models and each Centurion model takes up the space of 3 models."
        },
        {
          "name": "Assault Ramp",
          "description": "Each time a unit disembarks from this model after it has made a Normal move, that unit is still eligible to declare a charge this turn."
        },
        {
          "name": "Legacy of Jerulas",
          "description": "In your Shooting phase, after this model has shot, select one enemy unit hit by one or more of those attacks. Until the end of the turn, each time a friendly model that disembarked from this TRANSPORT this turn makes an attack that targets that enemy unit, re-roll a Hit roll of 1 and a re-roll a Wound roll of 1"
        }
      ],
      "pricing": [
        {
          "range": "[1,2]",
          "label": "Your 1st To 2nd Units Cost",
          "costs": [
            {
              "models": 1,
              "points": 220
            }
          ]
        },
        {
          "range": "[3,)",
          "label": "Your 3rd + Unit Costs",
          "costs": [
            {
              "models": 1,
              "points": 240
            }
          ]
        }
      ],
      "pointsLabel": "220"
    },
    {
      "id": "a499-86fa-4d0c-b06d",
      "name": "Sternguard Veteran Squad",
      "points": 100,
      "keywords": [
        "Infantry",
        "Grenades",
        "Imperium",
        "Tacticus"
      ],
      "factionKeywords": [
        "Black Templars"
      ],
      "stats": {
        "M": "6\"",
        "T": "4",
        "SV": "3+",
        "W": "2",
        "LD": "6+",
        "OC": "1"
      },
      "rangedWeapons": [],
      "meleeWeapons": [
        {
          "name": "Astartes Chainsword",
          "range": "Melee",
          "A": "6",
          "WS": "3+",
          "S": "4",
          "AP": "-1",
          "D": "1",
          "keywords": []
        },
        {
          "name": "Power Weapon",
          "range": "Melee",
          "A": "5",
          "WS": "3+",
          "S": "5",
          "AP": "-2",
          "D": "1",
          "keywords": []
        },
        {
          "name": "Power Fist",
          "range": "Melee",
          "A": "4",
          "WS": "3+",
          "S": "8",
          "AP": "-2",
          "D": "2",
          "keywords": []
        }
      ],
      "abilities": [
        {
          "name": "Vitruous Onslaught",
          "description": "Each time a model in this unit makes an attack that targets the closest eligible target, you can re-roll a Wound roll of 1."
        }
      ],
      "pricing": [
        {
          "range": "[1,)",
          "label": "Your Unit Costs",
          "costs": [
            {
              "models": 5,
              "points": 100
            },
            {
              "models": 10,
              "points": 190
            }
          ]
        }
      ],
      "pointsLabel": "100/190"
    },
    {
      "id": "80ad-6e62-65e3-e667",
      "name": "Terminator Squad",
      "points": 160,
      "keywords": [
        "Infantry",
        "Imperium",
        "Terminator"
      ],
      "factionKeywords": [
        "Adeptus Astartes",
        "Black Templars"
      ],
      "stats": {
        "M": "5\"",
        "T": "5",
        "SV": "2+",
        "W": "3",
        "LD": "6+",
        "OC": "1"
      },
      "rangedWeapons": [],
      "meleeWeapons": [
        {
          "name": "Power Fist",
          "range": "Melee",
          "A": "3",
          "WS": "3+",
          "S": "8",
          "AP": "-2",
          "D": "2",
          "keywords": []
        }
      ],
      "abilities": [
        {
          "name": "Teleport Homer",
          "description": "At the start of the battle, you can set up one Teleport Homer token for this unit anywhere on the battlefield that is not in your opponent’s deployment zone. If you do, once per battle, you can target this unit with the Rapid Ingress Stratagem for 0CP, but when resolving that Stratagem, you must set this unit up within 3\" horizontally of that token and not within 9\" horizontally of any enemy models. That token is then removed."
        },
        {
          "name": "Judgement of the Weak",
          "description": "Each time an enemy unit (excluding MONSTERS and VEHICLES) within engagement range of this unit Falls Back, all models in that enemy unit must take a Desperate Escape test. When doing so, if that enemy unit is Battle-shocked, subtract 1 from each of those tests."
        }
      ],
      "pricing": [
        {
          "range": "[1,)",
          "label": "Your Unit Costs",
          "costs": [
            {
              "models": 5,
              "points": 160
            },
            {
              "models": 10,
              "points": 320
            }
          ]
        }
      ],
      "pointsLabel": "160/320"
    },
    {
      "id": "85b9-b304-a55c-30ef",
      "name": "Emperor's Champion (Anointed)",
      "points": 100,
      "keywords": [
        "Character",
        "Infantry",
        "Grenades",
        "Imperium",
        "Tacticus",
        "Emperor's Champion"
      ],
      "factionKeywords": [
        "Adeptus Astartes",
        "Black Templars"
      ],
      "stats": {
        "M": "8\"",
        "T": "4",
        "SV": "2+",
        "W": "5",
        "LD": "6+",
        "OC": "1"
      },
      "rangedWeapons": [],
      "meleeWeapons": [
        {
          "name": "Black Sword - Strike",
          "range": "Melee",
          "A": "6",
          "WS": "2+",
          "S": "8",
          "AP": "-3",
          "D": "3",
          "keywords": [
            "Anti-Character 5+",
            "Precision"
          ]
        },
        {
          "name": "Black Sword - Sweep",
          "range": "Melee",
          "A": "10",
          "WS": "2+",
          "S": "6",
          "AP": "-2",
          "D": "1",
          "keywords": []
        }
      ],
      "abilities": [
        {
          "name": "Armour of Faith",
          "description": "Once per phase, when an attack is allocated to this model and the saving throw is failed, you can change the Damage characteristic of that attack to 0."
        },
        {
          "name": "Sigismund's Heir",
          "description": "Each time this model's unit declares a charge, if one or more targets of that charge have the CHARACTER keyword, add 2 to the Charge roll. Once per battle, when this model's unit is selected to fight, if that unit is within Engagement Range of one or more enemy CHARACTER units, this model can use this ability. If it does, until the end of the phase, melee weapons equipped by this model have the [DEVASTATING WOUNDS] ability."
        },
        {
          "name": "Leader",
          "description": "This model can be attached to the following units:\n\n■ Assault Intercessor Squad\n■ Intercessor Squad\n■ Crusader Squad\n■ Sword Brethren\n■ Sternguard Veteran Squad"
        },
        {
          "name": "Chosen of the Emperor",
          "description": "You cannot include more than one **^^Emperor's Champion^^** model in your army."
        }
      ]
    }
  ],
  "enhancements": []
}
